{
	"backtraceGraph" : 
	{
		"commands" : 
		[
			"install"
		],
		"files" : 
		[
			"CMakeLists.txt"
		],
		"nodes" : 
		[
			{
				"file" : 0
			},
			{
				"command" : 0,
				"file" : 0,
				"line" : 154,
				"parent" : 0
			},
			{
				"command" : 0,
				"file" : 0,
				"line" : 160,
				"parent" : 0
			}
		]
	},
	"installers" : 
	[
		{
			"backtrace" : 1,
			"component" : "Unspecified",
			"destination" : "bin",
			"paths" : 
			[
				"app/main"
			],
			"targetId" : "main::@5f5a17c01335469806cb",
			"targetIndex" : 33,
			"type" : "target"
		},
		{
			"backtrace" : 2,
			"component" : "Unspecified",
			"destination" : "lib",
			"paths" : 
			[
				"src/func/libFunc.a"
			],
			"targetId" : "Func::@e3558a0b0f9211e18665",
			"targetIndex" : 20,
			"type" : "target"
		}
	],
	"paths" : 
	{
		"build" : ".",
		"source" : "."
	}
}
